drr/__init__.py
drr/batch_processor.py
drr/data_processor.py
drr/intrinsic_dimension_estimator.py
drr/main.py
drr-1.0.1.dist-info/licenses/LICENSE
drr-1.0.1.dist-info/METADATA
drr-1.0.1.dist-info/WHEEL
drr-1.0.1.dist-info/entry_points.txt
drr-1.0.1.dist-info/top_level.txt
drr-1.0.1.dist-info/RECORD
