Metadata-Version: 2.4
Name: drr
Version: 1.0.1
Summary: A professional Python toolkit for estimating intrinsic dimensionality and computing Dimensionality Reduction Ratio (DRR) metrics
Author-email: Andre Lustosa <dexmotta6@gmail.com>
Maintainer-email: Andre Lustosa <dexmotta6@gmail.com>
License: Unlicense
Project-URL: Homepage, https://github.com/andre-motta/dimensionality_reduction_ratio
Project-URL: Repository, https://github.com/andre-motta/dimensionality_reduction_ratio
Project-URL: Documentation, https://github.com/andre-motta/dimensionality_reduction_ratio#readme
Project-URL: Bug Tracker, https://github.com/andre-motta/dimensionality_reduction_ratio/issues
Project-URL: Changelog, https://github.com/andre-motta/dimensionality_reduction_ratio/releases
Keywords: dimensionality-reduction,intrinsic-dimension,machine-learning,data-analysis,correlation-function,levina-bickel
Classifier: Development Status :: 5 - Production/Stable
Classifier: Intended Audience :: Science/Research
Classifier: Intended Audience :: Developers
Classifier: License :: OSI Approved :: The Unlicense (Unlicense)
Classifier: Operating System :: OS Independent
Classifier: Programming Language :: Python :: 3
Classifier: Programming Language :: Python :: 3.11
Classifier: Programming Language :: Python :: 3.12
Classifier: Topic :: Scientific/Engineering :: Artificial Intelligence
Classifier: Topic :: Scientific/Engineering :: Information Analysis
Classifier: Topic :: Software Development :: Libraries :: Python Modules
Requires-Python: >=3.11
License-File: LICENSE
Requires-Dist: numpy<2.0.0,>=1.21.0
Requires-Dist: pandas<3.0.0,>=1.3.0
Requires-Dist: scipy<2.0.0,>=1.7.0
Requires-Dist: matplotlib<4.0.0,>=3.4.0
Requires-Dist: click<9.0.0,>=8.0.0
Provides-Extra: dev
Requires-Dist: flake8>=7.0.0; extra == "dev"
Requires-Dist: black>=25.0.0; extra == "dev"
Requires-Dist: isort>=6.0.0; extra == "dev"
Requires-Dist: pytest>=7.0.0; extra == "dev"
Requires-Dist: pytest-cov>=4.0.0; extra == "dev"
Provides-Extra: security
Requires-Dist: bandit>=1.7.0; extra == "security"
Requires-Dist: safety<3.0.0,>=2.0.0; extra == "security"
Provides-Extra: all
Requires-Dist: drr[dev,security]; extra == "all"
Dynamic: license-file
